gpwm/__init__.py
gpwm/cli.py
gpwm/utils.py
gpwm/stacks/__init__.py
gpwm/stacks/aws.py
gpwm/stacks/gcp.py
gpwm/stacks/shell.py
gpwm-1.0.0.dist-info/DESCRIPTION.rst
gpwm-1.0.0.dist-info/METADATA
gpwm-1.0.0.dist-info/RECORD
gpwm-1.0.0.dist-info/WHEEL
gpwm-1.0.0.dist-info/entry_points.txt
gpwm-1.0.0.dist-info/metadata.json
gpwm-1.0.0.dist-info/top_level.txt
